shapley_values/VERSION
shapley_values/__init__.py
shapley_values/shapley.py
shapley_values/x_shapley.py
shapley_values-1.0.1.dist-info/LICENSE
shapley_values-1.0.1.dist-info/METADATA
shapley_values-1.0.1.dist-info/WHEEL
shapley_values-1.0.1.dist-info/top_level.txt
shapley_values-1.0.1.dist-info/RECORD
